{"players": [{"name": "iakgnoh", "rank": 0, "lp": 416.0}, {"name": "Risen Rikan", "rank": 1, "lp": 274.0}, {"name": "Scathus", "rank": 2, "lp": 255.0}, {"name": "Cozmo", "rank": 3, "lp": 224.0}, {"name": "\u305b\u304b\u3044", "rank": 4, "lp": 222.0}, {"name": "D\u00ecor", "rank": 5, "lp": 213.0}, {"name": "Xemacs", "rank": 6, "lp": 211.0}, {"name": "AerosMacCousland", "rank": 7, "lp": 204.0}, {"name": "TTVNicMakesPlays", "rank": 8, "lp": 202.0}, {"name": "MAINBILLY", "rank": 9, "lp": 199.0}, {"name": "Cypher the First", "rank": 10, "lp": 188.0}, {"name": "Chicas", "rank": 11, "lp": 179.0}, {"name": "Sentient Thing", "rank": 12, "lp": 172.0}, {"name": "pYlObJosephine", "rank": 13, "lp": 167.0}, {"name": "Linferno", "rank": 14, "lp": 166.0}, {"name": "GeraldToppo", "rank": 15, "lp": 165.0}, {"name": "KryptonGold", "rank": 16, "lp": 150.0}, {"name": "Ichiran Ramen", "rank": 17, "lp": 150.0}, {"name": "LvM", "rank": 18, "lp": 150.0}, {"name": "AlphaCake", "rank": 19, "lp": 146.0}, {"name": "Stardrift", "rank": 20, "lp": 145.0}, {"name": "harry", "rank": 21, "lp": 130.0}, {"name": "RichGamebuddy", "rank": 22, "lp": 129.0}, {"name": "i v", "rank": 23, "lp": 129.0}, {"name": "hh1hh", "rank": 24, "lp": 128.0}, {"name": "Oblio", "rank": 25, "lp": 125.0}, {"name": "Lutrina", "rank": 26, "lp": 120.0}, {"name": "NoName", "rank": 27, "lp": 117.0}, {"name": "squallywag", "rank": 28, "lp": 116.0}, {"name": "deezL", "rank": 29, "lp": 115.0}, {"name": "Gardner", "rank": 30, "lp": 111.0}, {"name": "AlexTga", "rank": 31, "lp": 100.0}, {"name": "Darron", "rank": 32, "lp": 100.0}, {"name": "Carrot Spirit", "rank": 33, "lp": 100.0}, {"name": "Xemacs", "rank": 34, "lp": 100.0}, {"name": "Boolords", "rank": 35, "lp": 100.0}, {"name": "Cassane", "rank": 36, "lp": 100.0}, {"name": "Master Robo", "rank": 37, "lp": 100.0}, {"name": "Rumply Tie", "rank": 38, "lp": 100.0}, {"name": "ZACK", "rank": 39, "lp": 100.0}, {"name": " Kennen vai", "rank": 40, "lp": 100.0}, {"name": "BobxD", "rank": 41, "lp": 100.0}, {"name": "Deme Una Arepita", "rank": 42, "lp": 100.0}, {"name": "DeadlyKyuzo94", "rank": 43, "lp": 100.0}, {"name": "total", "rank": 44, "lp": 100.0}, {"name": "Sangyun3", "rank": 45, "lp": 99.0}, {"name": "RealPrismsword", "rank": 46, "lp": 98.0}, {"name": "Alffred", "rank": 47, "lp": 96.0}, {"name": "goophy", "rank": 48, "lp": 86.0}, {"name": " ZOMAXUS", "rank": 49, "lp": 84.0}, {"name": "Radonh", "rank": 50, "lp": 82.0}, {"name": "dedeuthe172", "rank": 51, "lp": 81.0}, {"name": "Akki", "rank": 52, "lp": 80.0}, {"name": "StopTypingPls", "rank": 53, "lp": 72.0}, {"name": "bigschman", "rank": 54, "lp": 67.0}, {"name": "Jubileu4002", "rank": 55, "lp": 67.0}, {"name": "thunderlight8", "rank": 56, "lp": 61.0}, {"name": "Phunkmasta", "rank": 57, "lp": 48.0}, {"name": "AhTiong0718", "rank": 58, "lp": 48.0}, {"name": "ANG3L", "rank": 59, "lp": 46.0}, {"name": "NASA07", "rank": 60, "lp": 39.0}, {"name": "dadda", "rank": 61, "lp": 34.0}, {"name": "UNBLOKCK1018", "rank": 62, "lp": 31.0}, {"name": "heloooo", "rank": 63, "lp": 31.0}, {"name": "MeatSpin", "rank": 64, "lp": 30.0}, {"name": "Torokbr", "rank": 65, "lp": 0.0}, {"name": "MONKEY D HULK", "rank": 66, "lp": 0.0}, {"name": "Spikeypacman", "rank": 67, "lp": 0.0}, {"name": "Konoldo", "rank": 68, "lp": 0.0}]}